{
  "id": "MZFS.EXE.20260715.000010",
  "record_type": "execution",
  "title": "Field Station Signal Loop / G0139 \u2014 REPAIR",
  "generated_at": "2026-07-15T18:47:02.963044Z",
  "generator_id": "MZFS.GEN.0002",
  "generator_version": "2.0.0",
  "family_id": "MZFS.FAM.0005",
  "seed": 218362332,
  "parent_ids": [
    "MZFS.EXE.20260715.000009"
  ],
  "status": "UNREVIEWED / RETAINED",
  "media_type": "video/mp4",
  "asset_uri": "../archive/executions/2026/07/MZFS.EXE.20260715.000010.mp4",
  "thumbnail_uri": "../archive/executions/2026/07/MZFS.EXE.20260715.000010.thumb.jpg",
  "source_ref": "scripts/generators/field_station_signal_loop.py",
  "dimensions": [
    960,
    720
  ],
  "checksum_sha256": "09e4bcd30cb5645d0cb6e3252a69f45032a1d08f4973a6ee2bf813e3ce5b9899",
  "thumbnail_checksum_sha256": "281571cb810224db4a56cdf3dce009fb70f0b845a819718ead742abf6f1496d6",
  "storage_policy": "repository-under-50mb",
  "tags": [
    "procedural",
    "scheduled-execution",
    "field-station"
  ],
  "lineage_generation": 139,
  "parent_archive_id": "MZFS.EXE.20260715.000009",
  "developmental_phase": "REPAIR",
  "topology": "distributed relation field",
  "node_count": 52,
  "connection_rules": {
    "nearest_neighbors": 2,
    "cross_cluster_bias": 0.46675300353435,
    "repair_bias": 0.35
  },
  "field_tension": 1.141,
  "drift_direction": {
    "x": -0.6647587983754015,
    "y": -0.5869247741886738
  },
  "growth_bias": {
    "x": 0.048519998582434,
    "y": 0.38638729229631985
  },
  "damage": 0.46,
  "residue": 0.909,
  "anomalies": [
    {
      "id": "ANOM-0025-01",
      "type": "orange_lock",
      "introduced_generation": 25,
      "persistent": true,
      "target": "E0024"
    },
    {
      "id": "ANOM-0036-02",
      "type": "orange_lock",
      "introduced_generation": 36,
      "persistent": true,
      "target": "E0036"
    },
    {
      "id": "ANOM-0086-03",
      "type": "persistent_residue",
      "introduced_generation": 86,
      "persistent": true
    },
    {
      "id": "ANOM-0111-04",
      "type": "persistent_residue",
      "introduced_generation": 111,
      "persistent": true
    }
  ],
  "palette_state": {
    "orange_ratio": 0.15535061704993702,
    "phosphor_energy": 1.2177875458070972,
    "desaturation": 0.0
  },
  "mutation_history": [
    {
      "scale": "iteration",
      "type": "continuous_drift",
      "value": {
        "field_tension": 1.141,
        "movement_speed": 0.727
      }
    }
  ],
  "metrics_before": {
    "node_count": 52,
    "cluster_count": 2,
    "connection_count": 51,
    "connectivity": 0.0385,
    "field_direction": {
      "x": -0.704,
      "y": -0.64
    },
    "anomaly_count": 4,
    "residue": 0.908,
    "symmetry": 0.714,
    "fragmentation": 0.0385,
    "movement_speed": 0.701,
    "phase": "REPAIR",
    "orange_ratio": 0.169,
    "damage": 0.46,
    "field_tension": 1.186
  },
  "metrics_after": {
    "node_count": 52,
    "cluster_count": 2,
    "connection_count": 51,
    "connectivity": 0.0385,
    "field_direction": {
      "x": -0.665,
      "y": -0.587
    },
    "anomaly_count": 4,
    "residue": 0.909,
    "symmetry": 0.713,
    "fragmentation": 0.0385,
    "movement_speed": 0.727,
    "phase": "REPAIR",
    "orange_ratio": 0.155,
    "damage": 0.46,
    "field_tension": 1.141
  },
  "key_change_type": "palette_shift",
  "key_change_value": -0.014,
  "key_change_certainty": "speculative",
  "key_change_text": "Recovery Agents detected a speculative palette shift toward phosphor signal. The change is measurable but may reflect a temporary state response rather than a permanent rule change.",
  "state_snapshot_uri": "../archive/states/field-station-signal-loop/MZFS.EXE.20260715.000010.json"
}
