{
  "id": "MZFS.EXE.20260714.000011",
  "record_type": "execution",
  "title": "Field Station Signal Loop / G0125 \u2014 REPAIR",
  "generated_at": "2026-07-14T19:27:42.005834Z",
  "generator_id": "MZFS.GEN.0002",
  "generator_version": "2.0.0",
  "family_id": "MZFS.FAM.0005",
  "seed": 181363399,
  "parent_ids": [
    "MZFS.EXE.20260714.000009"
  ],
  "status": "UNREVIEWED / RETAINED",
  "media_type": "video/mp4",
  "asset_uri": "../archive/executions/2026/07/MZFS.EXE.20260714.000011.mp4",
  "thumbnail_uri": "../archive/executions/2026/07/MZFS.EXE.20260714.000011.thumb.jpg",
  "source_ref": "scripts/generators/field_station_signal_loop.py",
  "dimensions": [
    960,
    720
  ],
  "checksum_sha256": "0cc5c3fac7efba68c25e7040acf505989b4d19fefb28c1bc0a72cae0ed1acb69",
  "thumbnail_checksum_sha256": "6746bdcb30686b80253cafc6b76ecd97c7b457ee635962a65a6a82aed50e4859",
  "storage_policy": "repository-under-50mb",
  "tags": [
    "procedural",
    "scheduled-execution",
    "field-station"
  ],
  "lineage_generation": 125,
  "parent_archive_id": "MZFS.EXE.20260714.000009",
  "developmental_phase": "REPAIR",
  "topology": "distributed relation field",
  "node_count": 52,
  "connection_rules": {
    "nearest_neighbors": 2,
    "cross_cluster_bias": 0.3330421911227622,
    "repair_bias": 0.35
  },
  "field_tension": 1.124,
  "drift_direction": {
    "x": -0.6455152842833304,
    "y": -0.6096222591583548
  },
  "growth_bias": {
    "x": 0.25189252258253075,
    "y": 0.10600426680375197
  },
  "damage": 0.46,
  "residue": 0.964,
  "anomalies": [
    {
      "id": "ANOM-0025-01",
      "type": "orange_lock",
      "introduced_generation": 25,
      "persistent": true,
      "target": "E0024"
    },
    {
      "id": "ANOM-0036-02",
      "type": "orange_lock",
      "introduced_generation": 36,
      "persistent": true,
      "target": "E0036"
    },
    {
      "id": "ANOM-0086-03",
      "type": "persistent_residue",
      "introduced_generation": 86,
      "persistent": true
    },
    {
      "id": "ANOM-0111-04",
      "type": "persistent_residue",
      "introduced_generation": 111,
      "persistent": true
    }
  ],
  "palette_state": {
    "orange_ratio": 0.2191074498368066,
    "phosphor_energy": 1.2372696539594292,
    "desaturation": 0.0
  },
  "mutation_history": [
    {
      "scale": "iteration",
      "type": "continuous_drift",
      "value": {
        "field_tension": 1.124,
        "movement_speed": 0.665
      }
    }
  ],
  "metrics_before": {
    "node_count": 52,
    "cluster_count": 2,
    "connection_count": 51,
    "connectivity": 0.0385,
    "field_direction": {
      "x": -0.559,
      "y": -0.545
    },
    "anomaly_count": 4,
    "residue": 0.975,
    "symmetry": 0.72,
    "fragmentation": 0.0385,
    "movement_speed": 0.674,
    "phase": "REPAIR",
    "orange_ratio": 0.206,
    "damage": 0.46,
    "field_tension": 1.095
  },
  "metrics_after": {
    "node_count": 52,
    "cluster_count": 2,
    "connection_count": 51,
    "connectivity": 0.0385,
    "field_direction": {
      "x": -0.646,
      "y": -0.61
    },
    "anomaly_count": 4,
    "residue": 0.964,
    "symmetry": 0.72,
    "fragmentation": 0.0385,
    "movement_speed": 0.665,
    "phase": "REPAIR",
    "orange_ratio": 0.219,
    "damage": 0.46,
    "field_tension": 1.124
  },
  "key_change_type": "palette_shift",
  "key_change_value": 0.013,
  "key_change_certainty": "speculative",
  "key_change_text": "Recovery Agents detected a speculative palette shift toward orange annotation. The change is measurable but may reflect a temporary state response rather than a permanent rule change.",
  "state_snapshot_uri": "../archive/states/field-station-signal-loop/MZFS.EXE.20260714.000011.json"
}
