{
  "id": "MZFS.EXE.20260706.000003",
  "record_type": "execution",
  "title": "Field Station Signal Loop / G0058 \u2014 ENTANGLEMENT",
  "generated_at": "2026-07-06T11:05:44.638614Z",
  "generator_id": "MZFS.GEN.0002",
  "generator_version": "2.0.0",
  "family_id": "MZFS.FAM.0005",
  "seed": 330375743,
  "parent_ids": [
    "MZFS.EXE.20260705.000014"
  ],
  "status": "UNREVIEWED / RETAINED",
  "media_type": "video/mp4",
  "asset_uri": "../archive/executions/2026/07/MZFS.EXE.20260706.000003.mp4",
  "thumbnail_uri": "../archive/executions/2026/07/MZFS.EXE.20260706.000003.thumb.jpg",
  "source_ref": "scripts/generators/field_station_signal_loop.py",
  "dimensions": [
    960,
    720
  ],
  "checksum_sha256": "18dfa90adf283b94a860ae87aa07a99b06123552118b3dd2b545c792d09144cc",
  "thumbnail_checksum_sha256": "b60bf33e8dfa530d8091cfe84d524909237668471bc42a6526fe52116edba8ba",
  "storage_policy": "repository-under-50mb",
  "tags": [
    "procedural",
    "scheduled-execution",
    "field-station"
  ],
  "lineage_generation": 58,
  "parent_archive_id": "MZFS.EXE.20260705.000014",
  "developmental_phase": "ENTANGLEMENT",
  "topology": "distributed relation field",
  "node_count": 43,
  "connection_rules": {
    "nearest_neighbors": 2,
    "cross_cluster_bias": 0.3330421911227622,
    "repair_bias": 0.35
  },
  "field_tension": 1.205,
  "drift_direction": {
    "x": -0.2197900393498261,
    "y": -0.2875947679261044
  },
  "growth_bias": {
    "x": 0.25189252258253075,
    "y": 0.10600426680375197
  },
  "damage": 0.24,
  "residue": 0.319,
  "anomalies": [
    {
      "id": "ANOM-0025-01",
      "type": "orange_lock",
      "introduced_generation": 25,
      "persistent": true,
      "target": "E0024"
    },
    {
      "id": "ANOM-0036-02",
      "type": "orange_lock",
      "introduced_generation": 36,
      "persistent": true,
      "target": "E0036"
    }
  ],
  "palette_state": {
    "orange_ratio": 0.13278800943092914,
    "phosphor_energy": 1.131013333598832,
    "desaturation": 0.0
  },
  "mutation_history": [
    {
      "scale": "iteration",
      "type": "continuous_drift",
      "value": {
        "field_tension": 1.205,
        "movement_speed": 0.821
      }
    }
  ],
  "metrics_before": {
    "node_count": 43,
    "cluster_count": 1,
    "connection_count": 45,
    "connectivity": 0.0498,
    "field_direction": {
      "x": -0.155,
      "y": -0.286
    },
    "anomaly_count": 2,
    "residue": 0.318,
    "symmetry": 0.721,
    "fragmentation": 0.0233,
    "movement_speed": 0.859,
    "phase": "ENTANGLEMENT",
    "orange_ratio": 0.135,
    "damage": 0.24,
    "field_tension": 1.204
  },
  "metrics_after": {
    "node_count": 43,
    "cluster_count": 1,
    "connection_count": 45,
    "connectivity": 0.0498,
    "field_direction": {
      "x": -0.22,
      "y": -0.288
    },
    "anomaly_count": 2,
    "residue": 0.319,
    "symmetry": 0.721,
    "fragmentation": 0.0233,
    "movement_speed": 0.821,
    "phase": "ENTANGLEMENT",
    "orange_ratio": 0.133,
    "damage": 0.24,
    "field_tension": 1.205
  },
  "key_change_type": "movement_speed",
  "key_change_value": -0.038,
  "key_change_certainty": "probable",
  "key_change_text": "Recovery Agents observed that the field's movement rule has slowed. The change is consistent across the current execution but requires further runs to establish persistence.",
  "state_snapshot_uri": "../archive/states/field-station-signal-loop/MZFS.EXE.20260706.000003.json"
}
